{"data":{"Year":[2021,2021,2021,2021,2021,2021],"UNIT_MEASURE":["NUMBER","NUMBER","NUMBER","NUMBER","NUMBER","NUMBER"],"Municipality":["Sarajevo","Mostar","Sarajevo","Mostar","Sarajevo","Mostar"],"Educational_attainment":["zavrsena skola","zavrsena skola","zavrsena skola","zavrsena skola","zavrsena skola","zavrsena skola"],"SEX":["_T","_T","M","M","F","F"],"Value":[23212,232125,232,232555,2312,23125]},"edges":{"From":["Municipality","Educational_attainment"],"To":["Educational_attainment","SEX"]}}