{
  "resources": [
    {
      "path": "data.csv",
      "name": "data",
      "profile": "tabular-data-resource",
      "scheme": "file",
      "format": "csv",
      "hashing": "md5",
      "encoding": "utf-8",
      "schema": {
        "fields": [
          {
            "name": "Year",
            "type": "integer",
            "title": "Година"
          },
          {
            "name": "UNIT_MEASURE",
            "type": "string",
            "title": "UNIT_MEASURE"
          },
          {
            "name": "AGE",
            "type": "string",
            "constraints": {
              "enum": [
                "15+",
                "18-24",
                "25-34",
                "25-35",
                "25-36",
                "34-44",
                "34-45",
                "34-46",
                "45-54",
                "45-55",
                "45-56",
                "55-64",
                "65+",
                ""
              ]
            },
            "title": "AGE"
          },
          {
            "name": "Entity",
            "type": "string",
            "constraints": {
              "enum": [
                "BiH",
                "Федерација БиХ",
                "Република Српска",
                ""
              ]
            },
            "title": "Ентитет"
          },
          {
            "name": "Value",
            "type": "number",
            "title": "Вриједност"
          }
        ]
      }
    }
  ],
  "profile": "data-package",
  "name": "4-1-1",
  "title": "Удио младих и одраслих са вјештинама информационих и комуникационих технологија (ИКТ), према врсти вјештине"
}